<chromosome id="23480" primary-parent-id="22198"><neuron id="0" type="in" activation="linear"/>
<neuron id="1" type="in" activation="linear"/>
<neuron id="2" type="in" activation="linear"/>
<neuron id="3" type="out" activation="sigmoid"/>
<connection id="5" src-id="1" dest-id="3" weight="-0.41574232504838815"/>
<connection id="208" src-id="3" dest-id="3" weight="-3.209011534516919"/>
<neuron id="219" type="hid" activation="sigmoid"/>
<connection id="220" src-id="2" dest-id="219" weight="-0.21081483364105225"/>
<connection id="221" src-id="219" dest-id="3" weight="-0.13521311115770263"/>
<neuron id="404" type="hid" activation="sigmoid"/>
<connection id="405" src-id="219" dest-id="404" weight="-6.984750398692478"/>
<neuron id="568" type="hid" activation="sigmoid"/>
<connection id="569" src-id="2" dest-id="568" weight="-13.604797314416674"/>
<connection id="570" src-id="568" dest-id="219" weight="-2.7795146375950996"/>
<connection id="902" src-id="0" dest-id="404" weight="1.9020064564402193"/>
<connection id="906" src-id="568" dest-id="3" weight="0.12862873437141842"/>
<connection id="912" src-id="1" dest-id="404" weight="2.7696906201252975"/>
<connection id="1083" src-id="1" dest-id="568" weight="-1.1219122037736562"/>
<connection id="1084" src-id="3" dest-id="404" weight="4.8941769036707825"/>
<neuron id="1088" type="hid" activation="sigmoid"/>
<connection id="1089" src-id="219" dest-id="1088" weight="-0.8933745495913152"/>
<connection id="1090" src-id="1088" dest-id="219" weight="4.80183439090208"/>
<connection id="1428" src-id="568" dest-id="1088" weight="1.8105153657128201"/>
<neuron id="1619" type="hid" activation="sigmoid"/>
<connection id="1620" src-id="404" dest-id="1619" weight="4.638957718228701"/>
<connection id="1810" src-id="0" dest-id="1088" weight="-2.3755982208691435"/>
<connection id="2345" src-id="219" dest-id="568" weight="-4.454481587279063"/>
<neuron id="3382" type="hid" activation="sigmoid"/>
<connection id="3383" src-id="3" dest-id="3382" weight="0.5035723430023715"/>
<connection id="3384" src-id="3382" dest-id="3" weight="1.5857801496898434"/>
<connection id="5078" src-id="1" dest-id="3382" weight="1.5259393998852413"/>
<neuron id="5084" type="hid" activation="sigmoid"/>
<connection id="5085" src-id="404" dest-id="5084" weight="-2.3591652616521994"/>
<connection id="5086" src-id="5084" dest-id="219" weight="1.3220199264323638"/>
<connection id="5251" src-id="2" dest-id="5084" weight="2.9854191500813787"/>
<connection id="5940" src-id="1619" dest-id="404" weight="2.761275818642154"/>
<connection id="6273" src-id="0" dest-id="5084" weight="0.9937189876659727"/>
<connection id="6786" src-id="219" dest-id="3382" weight="0.1749620537567791"/>
<connection id="8963" src-id="3" dest-id="1619" weight="0.9444567072781596"/>
<connection id="9133" src-id="1619" dest-id="219" weight="3.7284159207773415"/>
<connection id="11953" src-id="5084" dest-id="1619" weight="0.2967814436388656"/>
<neuron id="12286" type="hid" activation="sigmoid"/>
<connection id="12288" src-id="12286" dest-id="3" weight="-18.201144422136654"/>
<neuron id="13950" type="hid" activation="sigmoid"/>
<connection id="13952" src-id="13950" dest-id="12286" weight="3.3789062865876116"/>
<connection id="14286" src-id="12286" dest-id="12286" weight="4.5162162435462125"/>
<neuron id="14987" type="hid" activation="sigmoid"/>
<connection id="14988" src-id="1619" dest-id="14987" weight="-1.9617613643108847"/>
<connection id="14989" src-id="14987" dest-id="13950" weight="5.599514120798133"/>
<connection id="15157" src-id="13950" dest-id="13950" weight="0.05006932907885492"/>
<connection id="15496" src-id="404" dest-id="1088" weight="-2.282491752039678"/>
<connection id="17202" src-id="5084" dest-id="13950" weight="-3.5466629095248527"/>
<connection id="20162" src-id="14987" dest-id="12286" weight="1.3829293411186765"/>
<connection id="22151" src-id="14987" dest-id="3" weight="-0.7625902891159058"/>
<connection id="22153" src-id="1619" dest-id="3382" weight="-0.887277364730835"/>
</chromosome>